chef/__about__.py
chef/__init__.py
chef/client.py
okchef-1.2.5.dist-info/DESCRIPTION.rst
okchef-1.2.5.dist-info/METADATA
okchef-1.2.5.dist-info/RECORD
okchef-1.2.5.dist-info/WHEEL
okchef-1.2.5.dist-info/metadata.json
okchef-1.2.5.dist-info/top_level.txt
