Metadata-Version: 2.0
Name: okchef
Version: 1.2.5
Summary: python client library for Chef Server
Home-page: https://github.com/samstav/okchef
Author: Sam Stavinoha
Author-email: samuel.stavinoha@rackspace.com
License: Apache License, Version 2.0
Keywords: chef requests client api requests-chef 7311f24a
Platform: UNKNOWN
Classifier: Intended Audience :: Developers
Classifier: License :: OSI Approved :: Apache Software License
Classifier: Operating System :: OS Independent
Classifier: Topic :: Software Development
Classifier: Development Status :: 4 - Beta
Classifier: Programming Language :: Python
Classifier: Programming Language :: Python :: 2
Classifier: Programming Language :: Python :: 2.7
Classifier: Programming Language :: Python :: 3
Classifier: Programming Language :: Python :: 3.4
Requires-Dist: requests (>=2.7.0)
Requires-Dist: requests-chef (>=0.1.6)
Requires-Dist: six (>=1.9.0)
